<annotation>
	<folder>Detached House</folder>
	<filename>9000032.jpg</filename>
	<path>C:\Users\Rahul Verma\Dropbox\Tidyquant Team\Ashish\Labelled Images\Rooms\Detached House\000032.jpg</path>
	<source>
		<database>Unknown</database>
	</source>
	<size>
		<width>3210</width>
		<height>2707</height>
		<depth>1</depth>
	</size>
	<segmented>0</segmented>
	<object>
		<name>room</name>
		<pose>Unspecified</pose>
		<truncated>0</truncated>
		<difficult>0</difficult>
		<bndbox>
			<xmin>382</xmin>
			<ymin>626</ymin>
			<xmax>1195</xmax>
			<ymax>1482</ymax>
		</bndbox>
	</object>
	<object>
		<name>room</name>
		<pose>Unspecified</pose>
		<truncated>0</truncated>
		<difficult>0</difficult>
		<bndbox>
			<xmin>1552</xmin>
			<ymin>647</ymin>
			<xmax>2249</xmax>
			<ymax>1445</ymax>
		</bndbox>
	</object>
	<object>
		<name>room</name>
		<pose>Unspecified</pose>
		<truncated>0</truncated>
		<difficult>0</difficult>
		<bndbox>
			<xmin>373</xmin>
			<ymin>1439</ymin>
			<xmax>1211</xmax>
			<ymax>2191</ymax>
		</bndbox>
	</object>
	<object>
		<name>room</name>
		<pose>Unspecified</pose>
		<truncated>0</truncated>
		<difficult>0</difficult>
		<bndbox>
			<xmin>1174</xmin>
			<ymin>1444</ymin>
			<xmax>2757</xmax>
			<ymax>2187</ymax>
		</bndbox>
	</object>
	<object>
		<name>room</name>
		<pose>Unspecified</pose>
		<truncated>0</truncated>
		<difficult>0</difficult>
		<bndbox>
			<xmin>1161</xmin>
			<ymin>645</ymin>
			<xmax>1607</xmax>
			<ymax>1099</ymax>
		</bndbox>
	</object>
	<object>
		<name>room</name>
		<pose>Unspecified</pose>
		<truncated>0</truncated>
		<difficult>0</difficult>
		<bndbox>
			<xmin>2240</xmin>
			<ymin>637</ymin>
			<xmax>2765</xmax>
			<ymax>1432</ymax>
		</bndbox>
	</object>
	<object>
		<name>room</name>
		<pose>Unspecified</pose>
		<truncated>0</truncated>
		<difficult>0</difficult>
		<bndbox>
			<xmin>1899</xmin>
			<ymin>237</ymin>
			<xmax>2765</xmax>
			<ymax>632</ymax>
		</bndbox>
	</object>
</annotation>
