<annotation>
	<folder>Flats</folder>
	<filename>d000003.png</filename>
	<path>C:\Users\Rahul Verma\Dropbox\Tidyquant Team\Ashish\Labelled Images\Walls\Flats\000003.png</path>
	<source>
		<database>Unknown</database>
	</source>
	<size>
		<width>1762</width>
		<height>1408</height>
		<depth>3</depth>
	</size>
	<segmented>0</segmented>
	<object>
		<name>wall</name>
		<pose>Unspecified</pose>
		<truncated>0</truncated>
		<difficult>0</difficult>
		<bndbox>
			<xmin>349</xmin>
			<ymin>288</ymin>
			<xmax>375</xmax>
			<ymax>1112</ymax>
		</bndbox>
	</object>
	<object>
		<name>wall</name>
		<pose>Unspecified</pose>
		<truncated>0</truncated>
		<difficult>0</difficult>
		<bndbox>
			<xmin>1381</xmin>
			<ymin>288</ymin>
			<xmax>1405</xmax>
			<ymax>1105</ymax>
		</bndbox>
	</object>
	<object>
		<name>wall</name>
		<pose>Unspecified</pose>
		<truncated>0</truncated>
		<difficult>0</difficult>
		<bndbox>
			<xmin>358</xmin>
			<ymin>1090</ymin>
			<xmax>460</xmax>
			<ymax>1114</ymax>
		</bndbox>
	</object>
	<object>
		<name>wall</name>
		<pose>Unspecified</pose>
		<truncated>0</truncated>
		<difficult>0</difficult>
		<bndbox>
			<xmin>571</xmin>
			<ymin>1088</ymin>
			<xmax>694</xmax>
			<ymax>1116</ymax>
		</bndbox>
	</object>
	<object>
		<name>wall</name>
		<pose>Unspecified</pose>
		<truncated>0</truncated>
		<difficult>0</difficult>
		<bndbox>
			<xmin>911</xmin>
			<ymin>1088</ymin>
			<xmax>1030</xmax>
			<ymax>1112</ymax>
		</bndbox>
	</object>
	<object>
		<name>wall</name>
		<pose>Unspecified</pose>
		<truncated>0</truncated>
		<difficult>0</difficult>
		<bndbox>
			<xmin>1135</xmin>
			<ymin>1084</ymin>
			<xmax>1196</xmax>
			<ymax>1116</ymax>
		</bndbox>
	</object>
	<object>
		<name>wall</name>
		<pose>Unspecified</pose>
		<truncated>0</truncated>
		<difficult>0</difficult>
		<bndbox>
			<xmin>1294</xmin>
			<ymin>1080</ymin>
			<xmax>1415</xmax>
			<ymax>1110</ymax>
		</bndbox>
	</object>
	<object>
		<name>wall</name>
		<pose>Unspecified</pose>
		<truncated>0</truncated>
		<difficult>0</difficult>
		<bndbox>
			<xmin>898</xmin>
			<ymin>673</ymin>
			<xmax>1403</xmax>
			<ymax>688</ymax>
		</bndbox>
	</object>
	<object>
		<name>wall</name>
		<pose>Unspecified</pose>
		<truncated>0</truncated>
		<difficult>0</difficult>
		<bndbox>
			<xmin>564</xmin>
			<ymin>280</ymin>
			<xmax>732</xmax>
			<ymax>314</ymax>
		</bndbox>
	</object>
	<object>
		<name>wall</name>
		<pose>Unspecified</pose>
		<truncated>0</truncated>
		<difficult>0</difficult>
		<bndbox>
			<xmin>873</xmin>
			<ymin>284</ymin>
			<xmax>1075</xmax>
			<ymax>310</ymax>
		</bndbox>
	</object>
	<object>
		<name>wall</name>
		<pose>Unspecified</pose>
		<truncated>0</truncated>
		<difficult>0</difficult>
		<bndbox>
			<xmin>1294</xmin>
			<ymin>282</ymin>
			<xmax>1411</xmax>
			<ymax>316</ymax>
		</bndbox>
	</object>
	<object>
		<name>wall</name>
		<pose>Unspecified</pose>
		<truncated>0</truncated>
		<difficult>0</difficult>
		<bndbox>
			<xmin>583</xmin>
			<ymin>314</ymin>
			<xmax>586</xmax>
			<ymax>556</ymax>
		</bndbox>
	</object>
	<object>
		<name>wall</name>
		<pose>Unspecified</pose>
		<truncated>0</truncated>
		<difficult>0</difficult>
		<bndbox>
			<xmin>892</xmin>
			<ymin>314</ymin>
			<xmax>896</xmax>
			<ymax>561</ymax>
		</bndbox>
	</object>
	<object>
		<name>wall</name>
		<pose>Unspecified</pose>
		<truncated>0</truncated>
		<difficult>0</difficult>
		<bndbox>
			<xmin>362</xmin>
			<ymin>652</ymin>
			<xmax>452</xmax>
			<ymax>654</ymax>
		</bndbox>
	</object>
	<object>
		<name>wall</name>
		<pose>Unspecified</pose>
		<truncated>0</truncated>
		<difficult>0</difficult>
		<bndbox>
			<xmin>354</xmin>
			<ymin>537</ymin>
			<xmax>460</xmax>
			<ymax>539</ymax>
		</bndbox>
	</object>
	<object>
		<name>wall</name>
		<pose>Unspecified</pose>
		<truncated>0</truncated>
		<difficult>0</difficult>
		<bndbox>
			<xmin>564</xmin>
			<ymin>533</ymin>
			<xmax>728</xmax>
			<ymax>542</ymax>
		</bndbox>
	</object>
	<object>
		<name>wall</name>
		<pose>Unspecified</pose>
		<truncated>0</truncated>
		<difficult>0</difficult>
		<bndbox>
			<xmin>583</xmin>
			<ymin>676</ymin>
			<xmax>769</xmax>
			<ymax>686</ymax>
		</bndbox>
	</object>
	<object>
		<name>wall</name>
		<pose>Unspecified</pose>
		<truncated>0</truncated>
		<difficult>0</difficult>
		<bndbox>
			<xmin>820</xmin>
			<ymin>533</ymin>
			<xmax>975</xmax>
			<ymax>539</ymax>
		</bndbox>
	</object>
</annotation>
