<annotation>
	<folder>train</folder>
	<filename>rgb_3469 - Copy - Copy - Copy.png</filename>
	<path>C:\Users\ArunOnedata\Desktop\50images\4th-set-room\train\rgb_3469 - Copy - Copy - Copy.png</path>
	<source>
		<database>Unknown</database>
	</source>
	<size>
		<width>1754</width>
		<height>2480</height>
		<depth>1</depth>
	</size>
	<segmented>0</segmented>
	<object>
		<name>room</name>
		<pose>Unspecified</pose>
		<truncated>0</truncated>
		<difficult>0</difficult>
		<bndbox>
			<xmin>1117</xmin>
			<ymin>497</ymin>
			<xmax>1317</xmax>
			<ymax>975</ymax>
		</bndbox>
	</object>
	<object>
		<name>room</name>
		<pose>Unspecified</pose>
		<truncated>0</truncated>
		<difficult>0</difficult>
		<bndbox>
			<xmin>224</xmin>
			<ymin>261</ymin>
			<xmax>862</xmax>
			<ymax>977</ymax>
		</bndbox>
	</object>
	<object>
		<name>room</name>
		<pose>Unspecified</pose>
		<truncated>0</truncated>
		<difficult>0</difficult>
		<bndbox>
			<xmin>848</xmin>
			<ymin>261</ymin>
			<xmax>1132</xmax>
			<ymax>400</ymax>
		</bndbox>
	</object>
</annotation>
