<annotation>
	<folder>train</folder>
	<filename>single40319.jpg</filename>
	<path>C:\Users\ArunOnedata\Desktop\All\190_Images_arun\windows\train\single40319.jpg</path>
	<source>
		<database>Unknown</database>
	</source>
	<size>
		<width>4961</width>
		<height>3508</height>
		<depth>3</depth>
	</size>
	<segmented>0</segmented>
	<object>
		<name>window</name>
		<pose>Unspecified</pose>
		<truncated>0</truncated>
		<difficult>0</difficult>
		<bndbox>
			<xmin>986</xmin>
			<ymin>1482</ymin>
			<xmax>1062</xmax>
			<ymax>2027</ymax>
		</bndbox>
	</object>
	<object>
		<name>window</name>
		<pose>Unspecified</pose>
		<truncated>0</truncated>
		<difficult>0</difficult>
		<bndbox>
			<xmin>2969</xmin>
			<ymin>546</ymin>
			<xmax>3525</xmax>
			<ymax>625</ymax>
		</bndbox>
	</object>
	<object>
		<name>window</name>
		<pose>Unspecified</pose>
		<truncated>0</truncated>
		<difficult>0</difficult>
		<bndbox>
			<xmin>1113</xmin>
			<ymin>2979</ymin>
			<xmax>1661</xmax>
			<ymax>3049</ymax>
		</bndbox>
	</object>
	<object>
		<name>window</name>
		<pose>Unspecified</pose>
		<truncated>0</truncated>
		<difficult>0</difficult>
		<bndbox>
			<xmin>2637</xmin>
			<ymin>2978</ymin>
			<xmax>3186</xmax>
			<ymax>3064</ymax>
		</bndbox>
	</object>
</annotation>
